[
  {
    "id": "1498190599",
    "titulo": "PSP COM CAIXA DEFEITO LEIA BEM",
    "preco": 200,
    "precoRaw": "R$ 200",
    "categoria": "outros",
    "publicado": "",
    "detectado": "11:12",
    "tempoOlx": "",
    "descricao": "",
    "link": "https://mg.olx.com.br/belo-horizonte-e-regiao/games/consoles-de-video-game/psp-com-caixa-defeito-leia-bem-1498190599",
    "fotoUrl": "https://img.olx.com.br/images/38/382654511514338.jpg",
    "fotosUrls": [
      "https://img.olx.com.br/images/38/382654511514338.jpg",
      "https://img.olx.com.br/images/14/141692155081976.jpg",
      "https://img.olx.com.br/images/16/168645275067209.jpg",
      "https://img.olx.com.br/images/18/189657870252099.jpg"
    ],
    "defeito": false,
    "ts": 1777558371
  },
  {
    "id": "1481529186",
    "titulo": "Cabo original  Psvita FAT - com detalhes ",
    "preco": 115,
    "precoRaw": "R$ 115",
    "categoria": "outros",
    "publicado": "",
    "detectado": "11:12",
    "tempoOlx": "",
    "descricao": "",
    "link": "https://sp.olx.com.br/sao-paulo-e-regiao/games/consoles-de-video-game/cabo-original-psvita-fat-com-detalhes-1481529186",
    "fotoUrl": "https://img.olx.com.br/images/64/645661252452262.jpg",
    "fotosUrls": [
      "https://img.olx.com.br/images/64/645661252452262.jpg",
      "https://img.olx.com.br/images/67/673695251691828.jpg",
      "https://img.olx.com.br/images/69/697610493528917.jpg",
      "https://img.olx.com.br/images/71/711638010501294.jpg",
      "https://img.olx.com.br/images/74/745660375438800.jpg"
    ],
    "defeito": false,
    "ts": 1777558371
  },
  {
    "id": "1497924812",
    "titulo": "psp 1001",
    "preco": 375,
    "precoRaw": "R$ 375",
    "categoria": "outros",
    "publicado": "",
    "detectado": "11:12",
    "tempoOlx": "",
    "descricao": "",
    "link": "https://pr.olx.com.br/regiao-de-curitiba-e-paranagua/games/consoles-de-video-game/psp-1001-1497924812",
    "fotoUrl": "https://img.olx.com.br/images/67/672654639930733.jpg",
    "fotosUrls": [
      "https://img.olx.com.br/images/67/672654639930733.jpg",
      "https://img.olx.com.br/images/70/706639396246896.jpg",
      "https://img.olx.com.br/images/74/743636273799822.jpg",
      "https://img.olx.com.br/images/76/766670158440565.jpg",
      "https://img.olx.com.br/images/78/787611158884914.jpg",
      "https://img.olx.com.br/images/80/808626279932586.jpg"
    ],
    "defeito": false,
    "ts": 1777558371
  },
  {
    "id": "1497354442",
    "titulo": "PSP 2001 Game",
    "preco": 450,
    "precoRaw": "R$ 450",
    "categoria": "outros",
    "publicado": "",
    "detectado": "11:12",
    "tempoOlx": "",
    "descricao": "",
    "link": "https://sp.olx.com.br/sao-paulo-e-regiao/games/consoles-de-video-game/psp-2001-game-1497354442",
    "fotoUrl": "https://img.olx.com.br/images/33/331642152726768.jpg",
    "fotosUrls": [
      "https://img.olx.com.br/images/33/331642152726768.jpg",
      "https://img.olx.com.br/images/35/352612516987114.jpg",
      "https://img.olx.com.br/images/36/366602639502866.jpg",
      "https://img.olx.com.br/images/38/384617277948915.jpg",
      "https://img.olx.com.br/images/40/400637518021311.jpg",
      "https://img.olx.com.br/images/42/422610392086743.jpg"
    ],
    "defeito": false,
    "ts": 1777558371
  },
  {
    "id": "1488439356",
    "titulo": "PSP 2000 ",
    "preco": 500,
    "precoRaw": "R$ 500",
    "categoria": "outros",
    "publicado": "",
    "detectado": "11:12",
    "tempoOlx": "",
    "descricao": "",
    "link": "https://sp.olx.com.br/sao-paulo-e-regiao/games/consoles-de-video-game/psp-2000-1488439356",
    "fotoUrl": "https://img.olx.com.br/images/79/799641741156411.jpg",
    "fotosUrls": [
      "https://img.olx.com.br/images/79/799641741156411.jpg"
    ],
    "defeito": false,
    "ts": 1777558371
  },
  {
    "id": "1496672484",
    "titulo": "Game ",
    "preco": 250,
    "precoRaw": "R$ 250",
    "categoria": "outros",
    "publicado": "",
    "detectado": "11:12",
    "tempoOlx": "",
    "descricao": "",
    "link": "https://sp.olx.com.br/sao-paulo-e-regiao/games/consoles-de-video-game/game-1496672484",
    "fotoUrl": "https://img.olx.com.br/images/30/301603873583915.jpg",
    "fotosUrls": [
      "https://img.olx.com.br/images/30/301603873583915.jpg",
      "https://img.olx.com.br/images/33/335604758696596.jpg"
    ],
    "defeito": false,
    "ts": 1777558371
  },
  {
    "id": "1496200018",
    "titulo": "Miyoo Mini Plus",
    "preco": 600,
    "precoRaw": "R$ 600",
    "categoria": "outros",
    "publicado": "",
    "detectado": "11:12",
    "tempoOlx": "",
    "descricao": "",
    "link": "https://df.olx.com.br/distrito-federal-e-regiao/games/consoles-de-video-game/miyoo-mini-plus-1496200018",
    "fotoUrl": "https://img.olx.com.br/images/64/644666757123216.jpg",
    "fotosUrls": [
      "https://img.olx.com.br/images/64/644666757123216.jpg",
      "https://img.olx.com.br/images/64/645686756483349.jpg"
    ],
    "defeito": false,
    "ts": 1777558371
  },
  {
    "id": "1494895887",
    "titulo": "Vídeo game",
    "preco": 300,
    "precoRaw": "R$ 300",
    "categoria": "outros",
    "publicado": "",
    "detectado": "11:12",
    "tempoOlx": "",
    "descricao": "",
    "link": "https://pa.olx.com.br/regiao-de-santarem/games/consoles-de-video-game/video-game-1494895887",
    "fotoUrl": "https://img.olx.com.br/images/97/974659517907640.jpg",
    "fotosUrls": [
      "https://img.olx.com.br/images/97/974659517907640.jpg",
      "https://img.olx.com.br/images/98/988620635483473.jpg",
      "https://img.olx.com.br/images/99/991635152660670.jpg"
    ],
    "defeito": false,
    "ts": 1777558371
  },
  {
    "id": "1472680437",
    "titulo": " Destrave Definitivo Playstation Vita/ PS Vita",
    "preco": 69,
    "precoRaw": "R$ 69",
    "categoria": "outros",
    "publicado": "",
    "detectado": "11:12",
    "tempoOlx": "",
    "descricao": "",
    "link": "https://rj.olx.com.br/rio-de-janeiro-e-regiao/games/consoles-de-video-game/destrave-definitivo-playstation-vita-ps-vita-1472680437",
    "fotoUrl": "https://img.olx.com.br/images/62/628614005403347.jpg",
    "fotosUrls": [
      "https://img.olx.com.br/images/62/628614005403347.jpg",
      "https://img.olx.com.br/images/64/643644242577907.jpg",
      "https://img.olx.com.br/images/65/655623005748024.jpg",
      "https://img.olx.com.br/images/67/670684363611598.jpg",
      "https://img.olx.com.br/images/69/693617486493269.jpg",
      "https://img.olx.com.br/images/70/706684482531333.jpg"
    ],
    "defeito": false,
    "ts": 1777558371
  },
  {
    "id": "1493626957",
    "titulo": "Console portátil R35S + de 15.000 jogos 64gb",
    "preco": 279,
    "precoRaw": "R$ 279",
    "categoria": "outros",
    "publicado": "",
    "detectado": "11:12",
    "tempoOlx": "",
    "descricao": "",
    "link": "https://ma.olx.com.br/regiao-de-sao-luis/games/consoles-de-video-game/console-portatil-r35s-de-15-000-jogos-64gb-1493626957",
    "fotoUrl": "https://img.olx.com.br/images/73/739676634105434.jpg",
    "fotosUrls": [
      "https://img.olx.com.br/images/73/739676634105434.jpg",
      "https://img.olx.com.br/images/75/759636159284805.jpg"
    ],
    "defeito": false,
    "ts": 1777558371
  }
]